{
    "remove|autoremove|purge": null,
    "source": "_xfunc apt-cache _apt_cache_packages",
    "install|reinstall": null,
    "build-dep": null,
    "autoclean|indextargets": "_xfunc apt-cache _apt_cache_packages",
    "update": null,
    "upgrade": null,
    "dist-upgrade": null,
    "dselect-upgrade": null,
    "satisfy": null,
    "check": null,
    "download": null,
    "changelog": null,
    "clean": null,
    "--no-install-recommends": null,
    "--install-suggests": null,
    "--download-only": null,
    "--fix-broken": null,
    "--ignore-missing": null,
    "--fix-missing": null,
    "--no-download": null,
    "--quiet": null,
    "--simulate": null,
    "--just-print": null,
    "--dry-run": null,
    "--recon": null,
    "--no-act": null,
    "--yes": null,
    "--assume-yes": null,
    "--assume-no": null,
    "--no-show-upgraded": null,
    "--verbose-versions": null,
    "--host-architecture": null,
    "--build-profiles": null,
    "--compile": null,
    "--build": null,
    "--ignore-hold": null,
    "--with-new-pkgs": null,
    "--no-upgrade": null,
    "--only-upgrade": null,
    "--allow-downgrades": null,
    "--allow-remove-essential": null,
    "--allow-change-held-packages": null,
    "--force-yes": null,
    "--print-uris": null,
    "--purge": null,
    "--reinstall": null,
    "--list-cleanup": null,
    "--target-release|--default-release|-t": "apt-cache policy | command sed -ne 's/^ *release.*[ ,]o=\(Debian\|Ubuntu\),a=\(\w*\).*/\2/p'",
    "--trivial-only": null,
    "--no-remove": null,
    "--auto-remove": null,
    "--autoremove": null,
    "--only-source": null,
    "--diff-only": null,
    "--dsc-only": null,
    "--tar-only": null,
    "--arch-only": null,
    "--indep-only": null,
    "--allow-unauthenticated": null,
    "--no-allow-insecure-repositories": null,
    "--allow-releaseinfo-change": null,
    "--show-progress": null,
    "--with-source": null,
    "--error-on|--help|--version|--option|-e|-h|-v|-o": null,
    "--config-file|-c": "___advise_ls"
}